Azimuth/__init__.py
Azimuth/cluster_types.py
Azimuth/clusters.py
Azimuth/external_ips.py
Azimuth/kubernetes_app_templates.py
Azimuth/kubernetes_apps.py
Azimuth/kubernetes_cluster_templates.py
Azimuth/kubernetes_clusters.py
Azimuth/main.py
Azimuth/sizes.py
Azimuth/util.py
Azimuth/zenith.py
azimuth_robotframework-0.7.1.dist-info/LICENSE
azimuth_robotframework-0.7.1.dist-info/METADATA
azimuth_robotframework-0.7.1.dist-info/WHEEL
azimuth_robotframework-0.7.1.dist-info/top_level.txt
azimuth_robotframework-0.7.1.dist-info/RECORD
