Metadata-Version: 2.1
Name: azimuth-robotframework
Version: 0.7.1
Summary: Robot framework library for interacting with Azimuth.
Home-page: https://github.com/azimuth-cloud/azimuth-robotframework
Author: Matt Pryor
Author-email: matt@stackhpc.com
License-File: LICENSE
Requires-Dist: azimuth-sdk
Requires-Dist: easysemver
Requires-Dist: httpx
Requires-Dist: jsonschema-default
Requires-Dist: robotframework-pythonlibcore
Requires-Dist: selenium
